{
	"backtraceGraph" : 
	{
		"commands" : 
		[
			"install"
		],
		"files" : 
		[
			"library/asset/pds/CMakeLists.txt"
		],
		"nodes" : 
		[
			{
				"file" : 0
			},
			{
				"command" : 0,
				"file" : 0,
				"line" : 31,
				"parent" : 0
			}
		]
	},
	"installers" : 
	[
		{
			"backtrace" : 1,
			"component" : "plugin",
			"destination" : "bin/plugins",
			"paths" : 
			[
				"library/asset/pds/libpulchritude-asset-pds.dll"
			],
			"targetId" : "pulchritude-asset-pds::@305b333631809256a4ca",
			"targetIndex" : 7,
			"type" : "target"
		}
	],
	"paths" : 
	{
		"build" : "library/asset/pds",
		"source" : "library/asset/pds"
	}
}
